moby_distribution/__init__.py
moby_distribution/registry/__init__.py
moby_distribution/registry/auth.py
moby_distribution/registry/client.py
moby_distribution/registry/exceptions.py
moby_distribution/registry/resources/__init__.py
moby_distribution/registry/resources/blobs.py
moby_distribution/registry/resources/image.py
moby_distribution/registry/resources/manifests.py
moby_distribution/registry/resources/tags.py
moby_distribution/registry/utils.py
moby_distribution/spec/__init__.py
moby_distribution/spec/auth.py
moby_distribution/spec/base.py
moby_distribution/spec/endpoint.py
moby_distribution/spec/image_json.py
moby_distribution/spec/manifest.py
moby_distribution-0.8.2.dist-info/LICENSE
moby_distribution-0.8.2.dist-info/METADATA
moby_distribution-0.8.2.dist-info/WHEEL
moby_distribution-0.8.2.dist-info/RECORD
