Metadata-Version: 2.1
Name: moby-distribution
Version: 0.8.2
Summary: Yet another moby(docker) distribution implement by python.
Home-page: https://github.com/shabbywu/distribution
License: Apache-2.0
Author: shabbywu
Author-email: shabbywu@qq.com
Requires-Python: >=3.8,<4
Classifier: License :: OSI Approved :: Apache Software License
Classifier: Programming Language :: Python :: 3
Classifier: Programming Language :: Python :: 3.8
Classifier: Programming Language :: Python :: 3.9
Classifier: Programming Language :: Python :: 3.10
Classifier: Programming Language :: Python :: 3.11
Classifier: Programming Language :: Python :: 3.12
Requires-Dist: cryptography
Requires-Dist: curlify
Requires-Dist: py-libtrust (>=2.0.0)
Requires-Dist: pydantic (>=1.5)
Requires-Dist: requests (>=2.20.0)
Requires-Dist: www-authenticate (>=0.9.2,<0.10.0)
Project-URL: Repository, https://github.com/shabbywu/distribution
